hns_notification/__init__.py
hns_notification/opsgenie.py
hns_notification-20.3.dist-info/LICENSE
hns_notification-20.3.dist-info/METADATA
hns_notification-20.3.dist-info/WHEEL
hns_notification-20.3.dist-info/top_level.txt
hns_notification-20.3.dist-info/RECORD
