Metadata-Version: 2.1
Name: hns-notification
Version: 20.3
Summary: Thin wrappers around various notification systems
Home-page: https://gitlab.com/horsebridge/hns_notification.git
Author: Nitin Sidhu
Author-email: nitin.sidhu23@gmail.com
License: MIT
Platform: UNKNOWN
Classifier: License :: OSI Approved :: MIT License
Classifier: Operating System :: OS Independent
Classifier: Programming Language :: Python :: 3.6
Classifier: Programming Language :: Python :: 3.7
Classifier: Programming Language :: Python :: 3.8
Requires-Python: ~=3.6
Requires-Dist: opsgenie-sdk (<3,>=2)
